pySimpleBrainPlot/__init__.py
pySimpleBrainPlot/plotBrain.py
pySimpleBrainPlot/regionDescriptions.pkl
pySimpleBrainPlot/atlases/aparc_aseg_template.svg
pySimpleBrainPlot/atlases/aparc_template.svg
pySimpleBrainPlot/atlases/lausanne120_aseg_template.svg
pySimpleBrainPlot/atlases/lausanne120_template.svg
pySimpleBrainPlot/atlases/lausanne250_template.svg
pySimpleBrainPlot/atlases/wbb47_template.svg
pySimpleBrainPlot-0.0.4.dist-info/METADATA
pySimpleBrainPlot-0.0.4.dist-info/WHEEL
pySimpleBrainPlot-0.0.4.dist-info/top_level.txt
pySimpleBrainPlot-0.0.4.dist-info/RECORD
